nul/__init__.py
nul_lm-0.0.0.dist-info/LICENSE
nul_lm-0.0.0.dist-info/METADATA
nul_lm-0.0.0.dist-info/WHEEL
nul_lm-0.0.0.dist-info/top_level.txt
nul_lm-0.0.0.dist-info/RECORD
