Metadata-Version: 2.1
Name: nul-lm
Version: 0.0.0
Summary: nul
Home-page: 
Author: Francis Lim
Author-email: thyeem@gmail.com
License: MIT
Keywords: nul
Classifier: Topic :: Software Development :: Libraries :: Python Modules
Classifier: License :: OSI Approved :: MIT License
Classifier: Programming Language :: Python :: 3
Requires-Python: >=3.6
License-File: LICENSE
